openmines/__init__.py
openmines/src/__init__.py
openmines/src/charging_site.py
openmines/src/dispatcher.py
openmines/src/dump_site.py
openmines/src/load_site.py
openmines/src/mine.py
openmines/src/optimizer.py
openmines/src/road.py
openmines/src/truck.py
openmines/src/cli/__init__.py
openmines/src/cli/run.py
openmines/src/dispatch_algorithms/__init__.py
openmines/src/dispatch_algorithms/fixed_group_dispatcher.py
openmines/src/dispatch_algorithms/naive_dispatcher.py
openmines/src/dispatch_algorithms/nearest_dispatcher.py
openmines/src/dispatch_algorithms/optimize_dispatcher.py
openmines/src/dispatch_algorithms/ppo_dispatcher.py
openmines/src/dispatch_algorithms/pure_llm_dispatcher.py
openmines/src/dispatch_algorithms/random_dispatcher.py
openmines/src/dispatch_algorithms/rl_dispatch.py
openmines/src/dispatch_algorithms/shortest_trip_dispatcher.py
openmines/src/dispatch_algorithms/sptf_dispatcher.py
openmines/src/dispatch_algorithms/sq_dispatcher.py
openmines/src/dispatch_algorithms/tabu_optimizer_dispatcher.py
openmines/src/dispatch_algorithms/tabu_search_dispatch.py
openmines/src/utils/__init__.py
openmines/src/utils/analyzer.py
openmines/src/utils/event.py
openmines/src/utils/feature_processing.py
openmines/src/utils/logger.py
openmines/src/utils/rl_env.py
openmines/src/utils/ticker.py
openmines/src/utils/visualization/__init__.py
openmines/src/utils/visualization/charter.py
openmines/src/utils/visualization/graphher.py
openmines/src/utils/visualization/materials/dump.png
openmines/src/utils/visualization/materials/repair.png
openmines/src/utils/visualization/materials/truck_hauling.png
openmines/src/utils/visualization/materials/truck_initing.png
openmines/src/utils/visualization/materials/truck_unhauling.png
openmines/src/utils/visualization/materials/unrepairable.png
openmines/src/utils/visualization/materials/挖机.png
openmines/src/utils/visualization/materials/矿山.png
openmines-0.2.0.dist-info/LICENSE
openmines-0.2.0.dist-info/METADATA
openmines-0.2.0.dist-info/WHEEL
openmines-0.2.0.dist-info/entry_points.txt
openmines-0.2.0.dist-info/top_level.txt
openmines-0.2.0.dist-info/RECORD
