Metadata-Version: 2.2
Name: openmines
Version: 0.2.0
Summary: Mining Fleet Dispatch Algorithm Framework
Author: stone91
License: MIT
License-File: LICENSE
Requires-Dist: matplotlib==3.7.2
Requires-Dist: inflection
Requires-Dist: numpy==1.25.0
Requires-Dist: pandas==2.0.3
Requires-Dist: openai==0.27.8
Requires-Dist: pytest==7.4.0
Requires-Dist: scipy==1.10.1
Requires-Dist: simpy==4.0.2
Requires-Dist: tqdm==4.65.0
Requires-Dist: pyarrow==14.0.1
Requires-Dist: tyro==0.8.14
Requires-Dist: tensorboard==2.15.1
Requires-Dist: docutils==0.17.1
Requires-Dist: wandb==0.15.12
Requires-Dist: rich
Requires-Dist: gymnasium==0.28.1
Dynamic: author
Dynamic: license
Dynamic: requires-dist
Dynamic: summary
